<?xml version="1.0" encoding="UTF-8"?>
<con:soapui-project id="7722c0d8-62aa-411e-8c04-5211cbc26da7" activeEnvironment="Default" name="EmployeeApp" resourceRoot="" soapui-version="5.5.0" abortOnError="false" runType="SEQUENTIAL" xmlns:con="http://eviware.com/soapui/config"><con:settings/><con:interface xsi:type="con:WsdlInterface" id="1a0289ac-8b72-4c3a-8b94-0f2f5a33ed63" wsaVersion="NONE" name="EmployeeManagementServiceSoap12Binding" type="wsdl" bindingName="{http://sample.com/reservation/guest}EmployeeManagementServiceSoap12Binding" soapVersion="1_2" anonymous="optional" definition="http://localhost:8080/axis2/services/EmployeeManagementService?wsdl" xmlns:xsi="http://www.w3.org/2001/XMLSchema-instance"><con:settings/><con:definitionCache/><con:endpoints><con:endpoint>http://localhost:8080/axis2/services/EmployeeManagementService.EmployeeManagementServiceHttpSoap12Endpoint/</con:endpoint></con:endpoints><con:operation id="e465af0a-d55f-4f4d-b01c-1dfcf803b1f8" isOneWay="false" action="urn:addEmployee" name="addEmployee" bindingOperationName="addEmployee" type="Request-Response" inputName="" receivesAttachments="false" sendsAttachments="false" anonymous="optional"><con:settings/><con:call id="798eb99c-92e4-4f31-96a9-d2b5b112d280" name="Request 1"><con:settings/><con:encoding>UTF-8</con:encoding><con:endpoint>http://localhost:8080/axis2/services/EmployeeManagementService.EmployeeManagementServiceHttpSoap12Endpoint/</con:endpoint><con:request><![CDATA[<soap:Envelope xmlns:soap="http://www.w3.org/2003/05/soap-envelope" xmlns:typ="http://sample.com/reservation/guest/types">\r
   <soap:Header/>\r
   <soap:Body>\r
      <typ:addEmployee>\r
         <!--Optional:-->\r
         <typ:name>?</typ:name>\r
         <!--Optional:-->\r
         <typ:id>?</typ:id>\r
         <!--Optional:-->\r
         <typ:Department>?</typ:Department>\r
         <!--Optional:-->\r
         <typ:age>?</typ:age>\r
      </typ:addEmployee>\r
   </soap:Body>\r
</soap:Envelope>]]></con:request><con:jmsConfig JMSDeliveryMode="PERSISTENT"/><con:wsaConfig mustUnderstand="NONE" version="200508" action="urn:addEmployee"/></con:call></con:operation><con:operation id="b7149061-f1c4-4b6a-8ca4-da99384da9c4" isOneWay="false" action="urn:deleteEmployee" name="deleteEmployee" bindingOperationName="deleteEmployee" type="One-Way" inputName="" sendsAttachments="false" anonymous="optional"><con:settings/><con:call id="72b9c7a5-cf0a-42de-9918-1237a025e974" name="Request 1"><con:settings/><con:encoding>UTF-8</con:encoding><con:endpoint>http://localhost:8080/axis2/services/EmployeeManagementService.EmployeeManagementServiceHttpSoap12Endpoint/</con:endpoint><con:request><![CDATA[<soap:Envelope xmlns:soap="http://www.w3.org/2003/05/soap-envelope" xmlns:typ="http://sample.com/reservation/guest/types">\r
   <soap:Header/>\r
   <soap:Body>\r
      <typ:deleteEmployee>\r
         <!--Optional:-->\r
         <typ:employeeName>?</typ:employeeName>\r
      </typ:deleteEmployee>\r
   </soap:Body>\r
</soap:Envelope>]]></con:request><con:jmsConfig JMSDeliveryMode="PERSISTENT"/><con:wsaConfig mustUnderstand="NONE" version="200508" action="urn:deleteEmployee"/></con:call></con:operation><con:operation id="097f0e9c-8a8a-4e72-93d7-926f2637d461" isOneWay="false" action="urn:getEmployeeDetails" name="getEmployeeDetails" bindingOperationName="getEmployeeDetails" type="Request-Response" inputName="" receivesAttachments="false" sendsAttachments="false" anonymous="optional"><con:settings/><con:call id="b8cc902a-6246-457c-8383-30c18e141461" name="Request 1"><con:settings/><con:encoding>UTF-8</con:encoding><con:endpoint>http://localhost:8080/axis2/services/EmployeeManagementService.EmployeeManagementServiceHttpSoap12Endpoint/</con:endpoint><con:request><![CDATA[<soap:Envelope xmlns:soap="http://www.w3.org/2003/05/soap-envelope" xmlns:typ="http://sample.com/reservation/guest/types">\r
   <soap:Header/>\r
   <soap:Body>\r
      <typ:getEmployeeDetails>\r
         <!--Optional:-->\r
         <typ:employeeName>?</typ:employeeName>\r
      </typ:getEmployeeDetails>\r
   </soap:Body>\r
</soap:Envelope>]]></con:request><con:jmsConfig JMSDeliveryMode="PERSISTENT"/><con:wsaConfig mustUnderstand="NONE" version="200508" action="urn:getEmployeeDetails"/></con:call></con:operation></con:interface><con:interface xsi:type="con:WsdlInterface" id="52fd79d0-4ae5-443a-8c61-4822f3ac1d32" wsaVersion="NONE" name="EmployeeManagementServiceSoap11Binding" type="wsdl" bindingName="{http://sample.com/reservation/guest}EmployeeManagementServiceSoap11Binding" soapVersion="1_1" anonymous="optional" definition="http://localhost:8080/axis2/services/EmployeeManagementService?wsdl" xmlns:xsi="http://www.w3.org/2001/XMLSchema-instance"><con:settings/><con:definitionCache type="TEXT" rootPart="http://localhost:8080/axis2/services/EmployeeManagementService?wsdl"><con:part><con:url>http://localhost:8080/axis2/services/EmployeeManagementService?wsdl</con:url><con:content><![CDATA[<wsdl:definitions targetNamespace="http://sample.com/reservation/guest" xmlns:wsdl="http://schemas.xmlsoap.org/wsdl/" xmlns:ns="http://sample.com/reservation/guest/types" xmlns:wsaw="http://www.w3.org/2006/05/addressing/wsdl" xmlns:mime="http://schemas.xmlsoap.org/wsdl/mime/" xmlns:tns="http://sample.com/reservation/guest" xmlns:http="http://schemas.xmlsoap.org/wsdl/http/" xmlns:xs="http://www.w3.org/2001/XMLSchema" xmlns:ax21="http://exception.reservation.sample.com/xsd" xmlns:soap12="http://schemas.xmlsoap.org/wsdl/soap12/" xmlns:ns1="http://org.apache.axis2/xsd" xmlns:soap="http://schemas.xmlsoap.org/wsdl/soap/">
  <wsdl:documentation>EmployeeManagementService</wsdl:documentation>
  <wsdl:types>
    <xs:schema attributeFormDefault="qualified" elementFormDefault="qualified" targetNamespace="http://exception.reservation.sample.com/xsd">
      <xs:complexType name="EmployeeManagementException">
        <xs:sequence>
          <xs:element minOccurs="0" name="message" nillable="true" type="xs:string"/>
        </xs:sequence>
      </xs:complexType>
    </xs:schema>
    <xs:schema attributeFormDefault="qualified" elementFormDefault="qualified" targetNamespace="http://sample.com/reservation/guest/types" xmlns:ax22="http://exception.reservation.sample.com/xsd">
      <xs:import namespace="http://exception.reservation.sample.com/xsd"/>
      <xs:element name="EmployeeManagementServiceEmployeeManagementException">
        <xs:complexType>
          <xs:sequence>
            <xs:element minOccurs="0" name="EmployeeManagementException" nillable="true" type="ax22:EmployeeManagementException"/>
          </xs:sequence>
        </xs:complexType>
      </xs:element>
      <xs:element name="addEmployee">
        <xs:complexType>
          <xs:sequence>
            <xs:element minOccurs="0" name="name" nillable="true" type="xs:string"/>
            <xs:element minOccurs="0" name="id" nillable="true" type="xs:string"/>
            <xs:element minOccurs="0" name="Department" nillable="true" type="xs:string"/>
            <xs:element minOccurs="0" name="age" type="xs:int"/>
          </xs:sequence>
        </xs:complexType>
      </xs:element>
      <xs:element name="addEmployeeResponse">
        <xs:complexType>
          <xs:sequence>
            <xs:element minOccurs="0" name="return" type="xs:boolean"/>
          </xs:sequence>
        </xs:complexType>
      </xs:element>
      <xs:element name="deleteEmployee">
        <xs:complexType>
          <xs:sequence>
            <xs:element minOccurs="0" name="employeeName" nillable="true" type="xs:string"/>
          </xs:sequence>
        </xs:complexType>
      </xs:element>
      <xs:element name="getEmployeeDetails">
        <xs:complexType>
          <xs:sequence>
            <xs:element minOccurs="0" name="employeeName" nillable="true" type="xs:string"/>
          </xs:sequence>
        </xs:complexType>
      </xs:element>
      <xs:element name="getEmployeeDetailsResponse">
        <xs:complexType>
          <xs:sequence>
            <xs:element minOccurs="0" name="return" nillable="true" type="ns:Employee"/>
          </xs:sequence>
        </xs:complexType>
      </xs:element>
      <xs:complexType name="Employee">
        <xs:sequence>
          <xs:element minOccurs="0" name="age" type="xs:int"/>
          <xs:element minOccurs="0" name="department" nillable="true" type="xs:string"/>
          <xs:element minOccurs="0" name="id" nillable="true" type="xs:string"/>
          <xs:element minOccurs="0" name="name" nillable="true" type="xs:string"/>
        </xs:sequence>
      </xs:complexType>
    </xs:schema>
  </wsdl:types>
  <wsdl:message name="getEmployeeDetailsRequest">
    <wsdl:part name="parameters" element="ns:getEmployeeDetails"/>
  </wsdl:message>
  <wsdl:message name="getEmployeeDetailsResponse">
    <wsdl:part name="parameters" element="ns:getEmployeeDetailsResponse"/>
  </wsdl:message>
  <wsdl:message name="EmployeeManagementServiceEmployeeManagementException">
    <wsdl:part name="parameters" element="ns:EmployeeManagementServiceEmployeeManagementException"/>
  </wsdl:message>
  <wsdl:message name="deleteEmployeeRequest">
    <wsdl:part name="parameters" element="ns:deleteEmployee"/>
  </wsdl:message>
  <wsdl:message name="addEmployeeRequest">
    <wsdl:part name="parameters" element="ns:addEmployee"/>
  </wsdl:message>
  <wsdl:message name="addEmployeeResponse">
    <wsdl:part name="parameters" element="ns:addEmployeeResponse"/>
  </wsdl:message>
  <wsdl:portType name="EmployeeManagementServicePortType">
    <wsdl:operation name="getEmployeeDetails">
      <wsdl:input message="tns:getEmployeeDetailsRequest" wsaw:Action="urn:getEmployeeDetails"/>
      <wsdl:output message="tns:getEmployeeDetailsResponse" wsaw:Action="urn:getEmployeeDetailsResponse"/>
      <wsdl:fault message="tns:EmployeeManagementServiceEmployeeManagementException" name="EmployeeManagementServiceEmployeeManagementException" wsaw:Action="urn:getEmployeeDetailsEmployeeManagementServiceEmployeeManagementException"/>
    </wsdl:operation>
    <wsdl:operation name="deleteEmployee">
      <wsdl:input message="tns:deleteEmployeeRequest" wsaw:Action="urn:deleteEmployee"/>
      <wsdl:fault message="tns:EmployeeManagementServiceEmployeeManagementException" name="EmployeeManagementServiceEmployeeManagementException" wsaw:Action="urn:deleteEmployeeEmployeeManagementServiceEmployeeManagementException"/>
    </wsdl:operation>
    <wsdl:operation name="addEmployee">
      <wsdl:input message="tns:addEmployeeRequest" wsaw:Action="urn:addEmployee"/>
      <wsdl:output message="tns:addEmployeeResponse" wsaw:Action="urn:addEmployeeResponse"/>
      <wsdl:fault message="tns:EmployeeManagementServiceEmployeeManagementException" name="EmployeeManagementServiceEmployeeManagementException" wsaw:Action="urn:addEmployeeEmployeeManagementServiceEmployeeManagementException"/>
    </wsdl:operation>
  </wsdl:portType>
  <wsdl:binding name="EmployeeManagementServiceSoap11Binding" type="tns:EmployeeManagementServicePortType">
    <soap:binding transport="http://schemas.xmlsoap.org/soap/http" style="document"/>
    <wsdl:operation name="getEmployeeDetails">
      <soap:operation soapAction="urn:getEmployeeDetails" style="document"/>
      <wsdl:input>
        <soap:body use="literal"/>
      </wsdl:input>
      <wsdl:output>
        <soap:body use="literal"/>
      </wsdl:output>
      <wsdl:fault name="EmployeeManagementServiceEmployeeManagementException">
        <soap:fault use="literal" name="EmployeeManagementServiceEmployeeManagementException"/>
      </wsdl:fault>
    </wsdl:operation>
    <wsdl:operation name="deleteEmployee">
      <soap:operation soapAction="urn:deleteEmployee" style="document"/>
      <wsdl:input>
        <soap:body use="literal"/>
      </wsdl:input>
      <wsdl:fault name="EmployeeManagementServiceEmployeeManagementException">
        <soap:fault use="literal" name="EmployeeManagementServiceEmployeeManagementException"/>
      </wsdl:fault>
    </wsdl:operation>
    <wsdl:operation name="addEmployee">
      <soap:operation soapAction="urn:addEmployee" style="document"/>
      <wsdl:input>
        <soap:body use="literal"/>
      </wsdl:input>
      <wsdl:output>
        <soap:body use="literal"/>
      </wsdl:output>
      <wsdl:fault name="EmployeeManagementServiceEmployeeManagementException">
        <soap:fault use="literal" name="EmployeeManagementServiceEmployeeManagementException"/>
      </wsdl:fault>
    </wsdl:operation>
  </wsdl:binding>
  <wsdl:binding name="EmployeeManagementServiceSoap12Binding" type="tns:EmployeeManagementServicePortType">
    <soap12:binding transport="http://schemas.xmlsoap.org/soap/http" style="document"/>
    <wsdl:operation name="getEmployeeDetails">
      <soap12:operation soapAction="urn:getEmployeeDetails" style="document"/>
      <wsdl:input>
        <soap12:body use="literal"/>
      </wsdl:input>
      <wsdl:output>
        <soap12:body use="literal"/>
      </wsdl:output>
      <wsdl:fault name="EmployeeManagementServiceEmployeeManagementException">
        <soap12:fault use="literal" name="EmployeeManagementServiceEmployeeManagementException"/>
      </wsdl:fault>
    </wsdl:operation>
    <wsdl:operation name="deleteEmployee">
      <soap12:operation soapAction="urn:deleteEmployee" style="document"/>
      <wsdl:input>
        <soap12:body use="literal"/>
      </wsdl:input>
      <wsdl:fault name="EmployeeManagementServiceEmployeeManagementException">
        <soap12:fault use="literal" name="EmployeeManagementServiceEmployeeManagementException"/>
      </wsdl:fault>
    </wsdl:operation>
    <wsdl:operation name="addEmployee">
      <soap12:operation soapAction="urn:addEmployee" style="document"/>
      <wsdl:input>
        <soap12:body use="literal"/>
      </wsdl:input>
      <wsdl:output>
        <soap12:body use="literal"/>
      </wsdl:output>
      <wsdl:fault name="EmployeeManagementServiceEmployeeManagementException">
        <soap12:fault use="literal" name="EmployeeManagementServiceEmployeeManagementException"/>
      </wsdl:fault>
    </wsdl:operation>
  </wsdl:binding>
  <wsdl:binding name="EmployeeManagementServiceHttpBinding" type="tns:EmployeeManagementServicePortType">
    <http:binding verb="POST"/>
    <wsdl:operation name="getEmployeeDetails">
      <http:operation location="getEmployeeDetails"/>
      <wsdl:input>
        <mime:content type="application/xml" part="parameters"/>
      </wsdl:input>
      <wsdl:output>
        <mime:content type="application/xml" part="parameters"/>
      </wsdl:output>
    </wsdl:operation>
    <wsdl:operation name="deleteEmployee">
      <http:operation location="deleteEmployee"/>
      <wsdl:input>
        <mime:content type="application/xml" part="parameters"/>
      </wsdl:input>
    </wsdl:operation>
    <wsdl:operation name="addEmployee">
      <http:operation location="addEmployee"/>
      <wsdl:input>
        <mime:content type="application/xml" part="parameters"/>
      </wsdl:input>
      <wsdl:output>
        <mime:content type="application/xml" part="parameters"/>
      </wsdl:output>
    </wsdl:operation>
  </wsdl:binding>
  <wsdl:service name="EmployeeManagementService">
    <wsdl:port name="EmployeeManagementServiceHttpSoap11Endpoint" binding="tns:EmployeeManagementServiceSoap11Binding">
      <soap:address location="http://localhost:8080/axis2/services/EmployeeManagementService.EmployeeManagementServiceHttpSoap11Endpoint/"/>
    </wsdl:port>
    <wsdl:port name="EmployeeManagementServiceHttpSoap12Endpoint" binding="tns:EmployeeManagementServiceSoap12Binding">
      <soap12:address location="http://localhost:8080/axis2/services/EmployeeManagementService.EmployeeManagementServiceHttpSoap12Endpoint/"/>
    </wsdl:port>
    <wsdl:port name="EmployeeManagementServiceHttpEndpoint" binding="tns:EmployeeManagementServiceHttpBinding">
      <http:address location="http://localhost:8080/axis2/services/EmployeeManagementService.EmployeeManagementServiceHttpEndpoint/"/>
    </wsdl:port>
  </wsdl:service>
</wsdl:definitions>]]></con:content><con:type>http://schemas.xmlsoap.org/wsdl/</con:type></con:part></con:definitionCache><con:endpoints><con:endpoint>http://localhost:8080/axis2/services/EmployeeManagementService.EmployeeManagementServiceHttpSoap11Endpoint/</con:endpoint></con:endpoints><con:operation id="e242401f-cc7b-48c7-8920-c1d78fb86856" isOneWay="false" action="urn:addEmployee" name="addEmployee" bindingOperationName="addEmployee" type="Request-Response" inputName="" receivesAttachments="false" sendsAttachments="false" anonymous="optional"><con:settings/><con:call id="51f7798a-2689-4327-9a5e-62b309e01b95" name="Request 1"><con:settings/><con:encoding>UTF-8</con:encoding><con:endpoint>http://localhost:8080/axis2/services/EmployeeManagementService.EmployeeManagementServiceHttpSoap11Endpoint/</con:endpoint><con:request><![CDATA[<soapenv:Envelope xmlns:soapenv="http://schemas.xmlsoap.org/soap/envelope/" xmlns:typ="http://sample.com/reservation/guest/types">\r
   <soapenv:Header/>\r
   <soapenv:Body>\r
      <typ:addEmployee>\r
         <!--Optional:-->\r
         <typ:name>?</typ:name>\r
         <!--Optional:-->\r
         <typ:id>?</typ:id>\r
         <!--Optional:-->\r
         <typ:Department>?</typ:Department>\r
         <!--Optional:-->\r
         <typ:age>?</typ:age>\r
      </typ:addEmployee>\r
   </soapenv:Body>\r
</soapenv:Envelope>]]></con:request><con:jmsConfig JMSDeliveryMode="PERSISTENT"/><con:wsaConfig mustUnderstand="NONE" version="200508" action="urn:addEmployee"/></con:call></con:operation><con:operation id="4d24ccf9-2bf4-4536-b71e-04df3edaa0ca" isOneWay="false" action="urn:deleteEmployee" name="deleteEmployee" bindingOperationName="deleteEmployee" type="One-Way" inputName="" sendsAttachments="false" anonymous="optional"><con:settings/><con:call id="d7f9ee41-a7d8-4146-bc6f-50d903534a39" name="Request 1"><con:settings/><con:encoding>UTF-8</con:encoding><con:endpoint>http://localhost:8080/axis2/services/EmployeeManagementService.EmployeeManagementServiceHttpSoap11Endpoint/</con:endpoint><con:request><![CDATA[<soapenv:Envelope xmlns:soapenv="http://schemas.xmlsoap.org/soap/envelope/" xmlns:typ="http://sample.com/reservation/guest/types">\r
   <soapenv:Header/>\r
   <soapenv:Body>\r
      <typ:deleteEmployee>\r
         <!--Optional:-->\r
         <typ:employeeName>?</typ:employeeName>\r
      </typ:deleteEmployee>\r
   </soapenv:Body>\r
</soapenv:Envelope>]]></con:request><con:jmsConfig JMSDeliveryMode="PERSISTENT"/><con:wsaConfig mustUnderstand="NONE" version="200508" action="urn:deleteEmployee"/></con:call></con:operation><con:operation id="6be6eeb8-a4c2-4c58-a777-bca801edbdbe" isOneWay="false" action="urn:getEmployeeDetails" name="getEmployeeDetails" bindingOperationName="getEmployeeDetails" type="Request-Response" inputName="" receivesAttachments="false" sendsAttachments="false" anonymous="optional"><con:settings/><con:call id="90661640-796d-46eb-aab7-3d1c0db3d1d8" name="Request 1"><con:settings/><con:encoding>UTF-8</con:encoding><con:endpoint>http://localhost:8080/axis2/services/EmployeeManagementService.EmployeeManagementServiceHttpSoap11Endpoint/</con:endpoint><con:request><![CDATA[<soapenv:Envelope xmlns:soapenv="http://schemas.xmlsoap.org/soap/envelope/" xmlns:typ="http://sample.com/reservation/guest/types">\r
   <soapenv:Header/>\r
   <soapenv:Body>\r
      <typ:getEmployeeDetails>\r
         <!--Optional:-->\r
         <typ:employeeName>?</typ:employeeName>\r
      </typ:getEmployeeDetails>\r
   </soapenv:Body>\r
</soapenv:Envelope>]]></con:request><con:jmsConfig JMSDeliveryMode="PERSISTENT"/><con:wsaConfig mustUnderstand="NONE" version="200508" action="urn:getEmployeeDetails"/></con:call></con:operation></con:interface><con:testSuite id="5b6cb06e-bfcf-4e17-870c-a4e68563781a" name="TestSuite 1"><con:settings/><con:runType>SEQUENTIAL</con:runType><con:testCase id="593150b8-e854-4786-a20a-019b7e1a5427" failOnError="true" failTestCaseOnErrors="true" keepSession="false" maxResults="0" name="TestCase 1" searchProperties="true"><con:settings/><con:testStep type="request" name="SOAP Request" id="273a7d16-246b-4374-afcc-0274d4a14025"><con:settings/><con:config xsi:type="con:RequestStep" xmlns:xsi="http://www.w3.org/2001/XMLSchema-instance"><con:interface>EmployeeManagementServiceSoap12Binding</con:interface><con:operation>addEmployee</con:operation><con:request name="SOAP Request" id="694f2247-61f8-4cdf-ae78-f2d1beba6f1e"><con:settings><con:setting id="com.eviware.soapui.impl.wsdl.WsdlRequest@request-headers">&lt;xml-fragment/></con:setting></con:settings><con:encoding>UTF-8</con:encoding><con:endpoint>http://localhost:8080/axis2/services/EmployeeManagementService.EmployeeManagementServiceHttpSoap12Endpoint/</con:endpoint><con:request><![CDATA[<soap:Envelope xmlns:soap="http://www.w3.org/2003/05/soap-envelope" xmlns:typ="http://sample.com/reservation/guest/types">\r
   <soap:Header/>\r
   <soap:Body>\r
      <typ:addEmployee>\r
         <!--Optional:-->\r
         <typ:name>${#TestCase#name}</typ:name>\r
         <!--Optional:-->\r
         <typ:id>${#TestCase#id}</typ:id>\r
         <!--Optional:-->\r
         <typ:Department>${#TestCase#dept}</typ:Department>\r
         <!--Optional:-->\r
         <typ:age>${#TestCase#dept}</typ:age>\r
      </typ:addEmployee>\r
   </soap:Body>\r
</soap:Envelope>]]></con:request><con:assertion type="SOAP Response" id="a769f9a5-dd1f-4709-ba80-aaad659802ee"/><con:assertion type="XPath Match" id="ef6a687a-055e-4f5b-87ab-2b774179779e" name="XPath Match"><con:configuration><path>declare namespace soapenv='http://www.w3.org/2003/05/soap-envelope';
declare namespace ns='http://sample.com/reservation/guest/types';
//ns:addEmployeeResponse</path><content>&lt;ns:addEmployeeResponse xmlns:ns="http://sample.com/reservation/guest/types" xmlns:soapenv="http://www.w3.org/2003/05/soap-envelope">
  &lt;ns:return>true&lt;/ns:return>
&lt;/ns:addEmployeeResponse></content><allowWildcards>false</allowWildcards><ignoreNamspaceDifferences>false</ignoreNamspaceDifferences><ignoreComments>false</ignoreComments></con:configuration></con:assertion><con:credentials><con:authType>No Authorization</con:authType></con:credentials><con:jmsConfig JMSDeliveryMode="PERSISTENT"/><con:jmsPropertyConfig/><con:wsaConfig mustUnderstand="NONE" version="200508"/><con:wsrmConfig version="1.2"/></con:request></con:config></con:testStep><con:testStep type="request" name="SOAP Request2" id="8fc38a91-fa17-4219-a12a-b2c1f1d80649"><con:settings/><con:config xsi:type="con:RequestStep" xmlns:xsi="http://www.w3.org/2001/XMLSchema-instance"><con:interface>EmployeeManagementServiceSoap12Binding</con:interface><con:operation>getEmployeeDetails</con:operation><con:request name="SOAP Request2" id="dc810968-2cac-4b08-9072-07dc203280c6"><con:settings><con:setting id="com.eviware.soapui.impl.wsdl.WsdlRequest@request-headers">&lt;xml-fragment/></con:setting></con:settings><con:encoding>UTF-8</con:encoding><con:endpoint>http://localhost:8080/axis2/services/EmployeeManagementService.EmployeeManagementServiceHttpSoap12Endpoint/</con:endpoint><con:request><![CDATA[<soap:Envelope xmlns:soap="http://www.w3.org/2003/05/soap-envelope" xmlns:typ="http://sample.com/reservation/guest/types">\r
   <soap:Header/>\r
   <soap:Body>\r
      <typ:getEmployeeDetails>\r
         <!--Optional:-->\r
         <typ:employeeName>Akshay</typ:employeeName>\r
      </typ:getEmployeeDetails>\r
   </soap:Body>\r
</soap:Envelope>]]></con:request><con:assertion type="Simple Contains" id="5b42c135-3406-4132-a9f3-4880e7a24a4b"><con:configuration/></con:assertion><con:assertion type="Simple NotContains" id="b0bb677d-8f46-4163-90e9-ec119bf54cd7" name="Not Contains"><con:configuration><token>true</token><ignoreCase>false</ignoreCase><useRegEx>false</useRegEx></con:configuration></con:assertion><con:assertion type="SOAP Response" id="f64d2fde-8f7e-4fc2-8183-37038cbeb21a" name="SOAP Response"/><con:assertion type="Invalid HTTP Status Codes" id="a90e284c-9549-40e5-b662-97bee32c79ca" name="Invalid HTTP Status Codes"><con:configuration><codes>400
</codes></con:configuration></con:assertion><con:assertion type="Valid HTTP Status Codes" id="dbb8599b-39cb-4cd9-ab6a-c25d84a81f01" name="Valid HTTP Status Codes"><con:configuration><codes>200</codes></con:configuration></con:assertion><con:assertion type="Response SLA Assertion" id="350914f1-cad9-4d42-bb99-55c8256932a9" name="Response SLA"><con:configuration><SLA>100</SLA></con:configuration></con:assertion><con:assertion type="Sensitive Information Exposure" id="fec431bb-580e-4984-81f5-cd1288303700" name="Sensitive Information Exposure"><con:configuration><AssertionSpecificExposureList>username###Akshay</AssertionSpecificExposureList><IncludeProjectSpecific>true</IncludeProjectSpecific><IncludeGlobal>true</IncludeGlobal></con:configuration></con:assertion><con:assertion type="XPath Match" id="69f73132-b30d-4746-b6b0-ce9fee89eeda" name="XPath Match"><con:configuration><path>declare namespace soapenv='http://www.w3.org/2003/05/soap-envelope';
declare namespace ns='http://sample.com/reservation/guest/types';
declare namespace ax21='http://exception.reservation.sample.com/xsd';
//ns:return</path><content><![CDATA[<ns:return xsi:type="ns:Employee" xmlns:ax21="http://exception.reservation.sample.com/xsd" xmlns:xsi="http://www.w3.org/2001/XMLSchema-instance" xmlns:ns="http://sample.com/reservation/guest/types" xmlns:soapenv="http://www.w3.org/2003/05/soap-envelope">
  <ns:age>23</ns:age>
  <ns:department>Testing</ns:department>
  <ns:id>300360</ns:id>
  <ns:name>Akshay</ns:name>
</ns:return>]]></content><allowWildcards>false</allowWildcards><ignoreNamspaceDifferences>false</ignoreNamspaceDifferences><ignoreComments>false</ignoreComments></con:configuration></con:assertion><con:credentials><con:authType>No Authorization</con:authType></con:credentials><con:jmsConfig JMSDeliveryMode="PERSISTENT"/><con:jmsPropertyConfig/><con:wsaConfig mustUnderstand="NONE" version="200508"/><con:wsrmConfig version="1.2"/></con:request></con:config></con:testStep><con:testStep type="request" name="SOAP Request3" id="5fa1ed98-5c5a-4549-a26c-3edf305d8e08"><con:settings/><con:config xsi:type="con:RequestStep" xmlns:xsi="http://www.w3.org/2001/XMLSchema-instance"><con:interface>EmployeeManagementServiceSoap12Binding</con:interface><con:operation>deleteEmployee</con:operation><con:request name="SOAP Request3" id="20460a76-a927-4ea6-8557-ee4a5e1fc7eb"><con:settings><con:setting id="com.eviware.soapui.impl.wsdl.WsdlRequest@request-headers">&lt;xml-fragment/></con:setting></con:settings><con:encoding>UTF-8</con:encoding><con:endpoint>http://localhost:8080/axis2/services/EmployeeManagementService.EmployeeManagementServiceHttpSoap12Endpoint/</con:endpoint><con:request><![CDATA[<soap:Envelope xmlns:soap="http://www.w3.org/2003/05/soap-envelope" xmlns:typ="http://sample.com/reservation/guest/types">\r
   <soap:Header/>\r
   <soap:Body>\r
      <typ:deleteEmployee>\r
         <!--Optional:-->\r
         <typ:employeeName>Akshay</typ:employeeName>\r
      </typ:deleteEmployee>\r
   </soap:Body>\r
</soap:Envelope>]]></con:request><con:assertion type="SOAP Response" id="7da37af0-99ff-456d-ab12-c088e696535f"/><con:credentials><con:authType>No Authorization</con:authType></con:credentials><con:jmsConfig JMSDeliveryMode="PERSISTENT"/><con:jmsPropertyConfig/><con:wsaConfig mustUnderstand="NONE" version="200508"/><con:wsrmConfig version="1.2"/></con:request></con:config></con:testStep><con:properties><con:property><con:name>name</con:name><con:value>rohit</con:value></con:property><con:property><con:name>age</con:name><con:value>28</con:value></con:property><con:property><con:name>id</con:name><con:value>5458</con:value></con:property><con:property><con:name>dept</con:name><con:value>Tesitng</con:value></con:property></con:properties></con:testCase><con:properties><con:property><con:name>dept</con:name><con:value>Testing</con:value></con:property><con:property><con:name>age</con:name><con:value>25</con:value></con:property></con:properties></con:testSuite><con:testSuite id="e44f2d70-3036-41e4-9f49-979e1584b39d" name="TestSuite"><con:settings/><con:runType>SEQUENTIAL</con:runType><con:testCase id="f86bd7d1-e9c7-4733-981c-51f0fa39a459" failOnError="true" failTestCaseOnErrors="true" keepSession="false" maxResults="0" name="addEmployee TestCase" searchProperties="true"><con:settings/><con:testStep type="request" id="ab7ae39b-946d-4b97-b8dd-1cf20165e663" name="addEmployee"><con:settings/><con:config xsi:type="con:RequestStep" xmlns:xsi="http://www.w3.org/2001/XMLSchema-instance"><con:interface>EmployeeManagementServiceSoap12Binding</con:interface><con:operation>addEmployee</con:operation><con:request name="addEmployee" id="e0b13b6d-db50-4861-a6ee-3fe049597160"><con:settings/><con:encoding>UTF-8</con:encoding><con:endpoint>http://localhost:8080/axis2/services/EmployeeManagementService.EmployeeManagementServiceHttpSoap12Endpoint/</con:endpoint><con:request><![CDATA[<soap:Envelope xmlns:soap="http://www.w3.org/2003/05/soap-envelope" xmlns:typ="http://sample.com/reservation/guest/types">\r
   <soap:Header/>\r
   <soap:Body>\r
      <typ:addEmployee>\r
         <!--Optional:-->\r
         <typ:name>?</typ:name>\r
         <!--Optional:-->\r
         <typ:id>?</typ:id>\r
         <!--Optional:-->\r
         <typ:Department>?</typ:Department>\r
         <!--Optional:-->\r
         <typ:age>?</typ:age>\r
      </typ:addEmployee>\r
   </soap:Body>\r
</soap:Envelope>]]></con:request><con:credentials><con:authType>No Authorization</con:authType></con:credentials><con:jmsConfig JMSDeliveryMode="PERSISTENT"/><con:jmsPropertyConfig/><con:wsaConfig action="urn:addEmployee" mustUnderstand="NONE" version="200508"/><con:wsrmConfig version="1.2"/></con:request></con:config></con:testStep><con:properties/></con:testCase><con:testCase id="9b05ac11-441d-4e54-a65c-217f7135c476" failOnError="true" failTestCaseOnErrors="true" keepSession="false" maxResults="0" name="deleteEmployee TestCase" searchProperties="true"><con:settings/><con:testStep type="request" id="9d3c448d-2dd5-4578-b032-dc4ef51c3f05" name="deleteEmployee"><con:settings/><con:config xsi:type="con:RequestStep" xmlns:xsi="http://www.w3.org/2001/XMLSchema-instance"><con:interface>EmployeeManagementServiceSoap12Binding</con:interface><con:operation>deleteEmployee</con:operation><con:request name="deleteEmployee" id="d5f8384e-c03e-4464-b928-4356a60a4ac0"><con:settings/><con:encoding>UTF-8</con:encoding><con:endpoint>http://localhost:8080/axis2/services/EmployeeManagementService.EmployeeManagementServiceHttpSoap12Endpoint/</con:endpoint><con:request><![CDATA[<soap:Envelope xmlns:soap="http://www.w3.org/2003/05/soap-envelope" xmlns:typ="http://sample.com/reservation/guest/types">\r
   <soap:Header/>\r
   <soap:Body>\r
      <typ:deleteEmployee>\r
         <!--Optional:-->\r
         <typ:employeeName>?</typ:employeeName>\r
      </typ:deleteEmployee>\r
   </soap:Body>\r
</soap:Envelope>]]></con:request><con:credentials><con:authType>No Authorization</con:authType></con:credentials><con:wsaConfig action="urn:deleteEmployee"/></con:request></con:config></con:testStep><con:properties/></con:testCase><con:testCase id="1e9b95e0-e13e-400b-98bb-70313206f8ef" failOnError="true" failTestCaseOnErrors="true" keepSession="false" maxResults="0" name="getEmployeeDetails TestCase" searchProperties="true"><con:settings/><con:testStep type="request" id="1b8bf56c-bf24-4aab-b01f-9c33499af350" name="getEmployeeDetails"><con:settings/><con:config xsi:type="con:RequestStep" xmlns:xsi="http://www.w3.org/2001/XMLSchema-instance"><con:interface>EmployeeManagementServiceSoap12Binding</con:interface><con:operation>getEmployeeDetails</con:operation><con:request name="getEmployeeDetails" id="84bf64ef-905f-403c-9328-03f01787e6c8"><con:settings/><con:encoding>UTF-8</con:encoding><con:endpoint>http://localhost:8080/axis2/services/EmployeeManagementService.EmployeeManagementServiceHttpSoap12Endpoint/</con:endpoint><con:request><![CDATA[<soap:Envelope xmlns:soap="http://www.w3.org/2003/05/soap-envelope" xmlns:typ="http://sample.com/reservation/guest/types">\r
   <soap:Header/>\r
   <soap:Body>\r
      <typ:getEmployeeDetails>\r
         <!--Optional:-->\r
         <typ:employeeName>?</typ:employeeName>\r
      </typ:getEmployeeDetails>\r
   </soap:Body>\r
</soap:Envelope>]]></con:request><con:credentials><con:authType>No Authorization</con:authType></con:credentials><con:wsaConfig action="urn:getEmployeeDetails"/></con:request></con:config></con:testStep><con:properties/></con:testCase><con:properties/></con:testSuite><con:properties><con:property><con:name>id</con:name><con:value>300375</con:value></con:property></con:properties><con:wssContainer/><con:oAuth2ProfileContainer/><con:oAuth1ProfileContainer/><con:sensitiveInformation/></con:soapui-project>